tremolo/__init__.py
tremolo/__main__.py
tremolo/asgi_lifespan.py
tremolo/asgi_server.py
tremolo/exceptions.py
tremolo/handlers.py
tremolo/http_server.py
tremolo/managers.py
tremolo/routes.py
tremolo/tremolo.py
tremolo/utils.py
tremolo/lib/__init__.py
tremolo/lib/connections.py
tremolo/lib/contexts.py
tremolo/lib/executors.py
tremolo/lib/http_exceptions.py
tremolo/lib/http_header.py
tremolo/lib/http_protocol.py
tremolo/lib/http_request.py
tremolo/lib/http_response.py
tremolo/lib/locks.py
tremolo/lib/queue.py
tremolo/lib/request.py
tremolo/lib/response.py
tremolo/lib/sse.py
tremolo/lib/websocket.py
tremolo-0.5.0.dist-info/licenses/LICENSE.txt
tremolo-0.5.0.dist-info/METADATA
tremolo-0.5.0.dist-info/WHEEL
tremolo-0.5.0.dist-info/top_level.txt
tremolo-0.5.0.dist-info/RECORD
