Metadata-Version: 2.4
Name: tremolo
Version: 0.5.0
Summary: Tremolo is a stream-oriented, asynchronous, programmable HTTP server written in pure Python. It can also serve as an ASGI server.
Author-email: Anggit Arfanto <contact@anggit.com>
License-Expression: MIT
Project-URL: Homepage, https://github.com/nggit/tremolo
Project-URL: Source, https://github.com/nggit/tremolo
Project-URL: Funding, https://github.com/sponsors/nggit
Classifier: Development Status :: 4 - Beta
Classifier: Operating System :: OS Independent
Classifier: Topic :: Internet :: WWW/HTTP :: HTTP Servers
Classifier: Topic :: Software Development :: Libraries :: Application Frameworks
Requires-Python: >=3.6
License-File: LICENSE.txt
Dynamic: license-file
